{
    "version": 10,
    "configurePresets": [
        {
            "name": "UCRT",
            "displayName": "GCC 15.1.0 x86_64-w64-mingw32 (UCRT64)",
            "description": "正在使用编译器: C = C:\\Env\\MSYS\\ucrt64\\bin\\gcc.exe, CXX = C:\\Env\\MSYS\\ucrt64\\bin\\g++.exe",
            "generator": "MinGW Makefiles",
            "binaryDir": "${sourceDir}/build/${presetName}",
            "environment": {
                "PATH": "C:/Env/MSYS/ucrt64/bin;$penv{PATH}"
            },
            "cacheVariables": {
                "CMAKE_INSTALL_PREFIX": "${sourceDir}/out/install/${presetName}",
                "CMAKE_C_COMPILER": "C:/Env/MSYS/ucrt64/bin/gcc.exe",
                "CMAKE_CXX_COMPILER": "C:/Env/MSYS/ucrt64/bin/g++.exe",
                "CMAKE_BUILD_TYPE": "Debug"
            }
        }
    ]
}